{
  "config": {
    "step": {
      "user": {
        "title": "Cync User Credentials",
        "description": "Please enter your Cync account credentials",
        "data": {
          "username": "Username",
          "password": "Password"
        }
      },
      "two_factor_code": {
        "title": "Cync Two-Factor Authentication",
        "description": "Please check your email and enter the two-factor code",
        "data": {
          "two_factor_code": "Two-Factor Code"
        }
      },
      "select_switches": {
        "title": "Select Devices to Add",
        "description": "Please select the rooms, groups, switches/bulbs, motion sensors, and ambient light sensors that you would like to add to Home Assistant",
        "data": {
          "rooms": "Rooms [room (home)]",
          "subgroups": "Groups [group (room:home)]",
          "switches": "Switches [switch/bulb (room:home)]",
          "motion_sensors": "Motion Sensors [sensor (room:home)]",
          "ambient_light_sensors": "Ambient Light Sensors [sensor (room:home)]"
        }
      }
    },
    "error": {
      "invalid_auth": "Invalid Cync user credentials or two-factor code.",
      "unknown": "Invalid or unsupported Cync configuration. Please ensure there is at least one Wi-Fi connected Cync device in your home(s)."
    },
    "abort": {
      "reauth_successful": "Reauthorization successful."
    }
  },
  "options": {
    "step": {
      "init": {
        "title": "Reload Cync Configuration",
        "description": "If you have added new devices to your Cync account, you can reauthorize to download your latest configuration.",
        "data": {
          "re_authenticate": "Reauthorize?"
        }
      },
      "two_factor_code": {
        "title": "Cync Two-Factor Authentication",
        "description": "Please check your email and enter the two-factor code",
        "data": {
          "two_factor_code": "Two-Factor Code"
        }
      },
      "select_switches": {
        "title": "Select Devices to Add",
        "description": "Please select the rooms, groups, switches/bulbs, motion sensors, and ambient light sensors that you would like to add to Home Assistant",
        "data": {
          "rooms": "Rooms [room (home)]",
          "subgroups": "Groups [group (room:home)]",
          "switches": "Switches [switch/bulb (room:home)]",
          "motion_sensors": "Motion Sensors [sensor (room:home)]",
          "ambient_light_sensors": "Ambient Light Sensors [sensor (room:home)]"
        }
      }
    },
    "error": {
      "invalid_auth": "Invalid Cync user credentials or two-factor code.",
      "unknown": "Invalid or unsupported Cync configuration. Please ensure there is at least one Wi-Fi connected Cync device in your home(s)."
    }
  }
}
